CHANGES.txt
MANIFEST.in
setup.py
cyclone_sse/__init__.py
cyclone_sse/amqp.py
cyclone_sse/brokers.py
cyclone_sse/handlers.py
cyclone_sse/periodic.py
cyclone_sse/server.py
cyclone_sse.egg-info/PKG-INFO
cyclone_sse.egg-info/SOURCES.txt
cyclone_sse.egg-info/dependency_links.txt
cyclone_sse.egg-info/requires.txt
cyclone_sse.egg-info/top_level.txt
twisted/plugins/cyclonesse_plugin.py