Metadata-Version: 1.0
Name: cyclone-sse
Version: 0.7.6
Summary: EventSource (SSE, Server-Sent Events) broadcasting server with channel support, Last-Event-Id etc, based on top of cyclone web server
Home-page: https://github.com/FZambia/cyclone-sse
Author: Alexandr Emelin
Author-email: frvzmb@gmail.com
License: http://www.apache.org/licenses/LICENSE-2.0
Keywords: python non-blocking twisted cyclone sse eventsource broadcast http redis amqp rabbitmq
Platform: UNKNOWN
